fastfsx/__init__.py
fastfsx/builder.py
fastfsx/exceptions.py
fastfsx/loader.py
fastfsx/path_utils.py
fastfsx/router.py
fastfsx-1.0.5.dist-info/METADATA
fastfsx-1.0.5.dist-info/WHEEL
fastfsx-1.0.5.dist-info/RECORD
