Metadata-Version: 2.3
Name: fastfsx
Version: 1.0.5
Summary: Filesystem-based router for FastAPI, inspired by Next.js `pages/`
License: MIT
Keywords: fastapi,router,filesystem,nextjs,pages
Author: LordCode
Author-email: 9999269010dddd@gmail.com
Requires-Python: >=3.11,<4.0
Classifier: Development Status :: 3 - Alpha
Classifier: Framework :: FastAPI
Classifier: Intended Audience :: Developers
Classifier: License :: OSI Approved :: MIT License
Classifier: Operating System :: OS Independent
Classifier: Programming Language :: Python :: 3
Classifier: Programming Language :: Python :: 3.11
Classifier: Programming Language :: Python :: 3.12
Classifier: Programming Language :: Python :: 3.13
Classifier: Topic :: Internet :: WWW/HTTP
Classifier: Topic :: Software Development :: Libraries
Requires-Dist: fastapi (>=0.115.0,<0.116.0)
Project-URL: Homepage, https://github.com/lordcod/fastfsx
Project-URL: Repository, https://github.com/lordcod/fastfsx
